metaclassifier/__init__.py
metaclassifier/__main__.py
metaclassifier/classify_reads.py
metaclassifier/process_reads.py
metaclassifier-1.0.1.dist-info/LICENSE
metaclassifier-1.0.1.dist-info/METADATA
metaclassifier-1.0.1.dist-info/WHEEL
metaclassifier-1.0.1.dist-info/entry_points.txt
metaclassifier-1.0.1.dist-info/top_level.txt
metaclassifier-1.0.1.dist-info/zip-safe
metaclassifier-1.0.1.dist-info/RECORD
