Metadata-Version: 2.1
Name: metaclassifier
Version: 1.0.1
Summary: MetaClassifier is an integrated pipeline for classifying and quantifying DNA metabarcoding data into taxonomy groups
Home-page: https://github.com/ewafula/MetaClassifier
Author: Eric Wafula
Author-email: ekw10@gmail.com
License: GNU General Public License v3 (GPLv3)
Platform: UNKNOWN
Classifier: License :: OSI Approved :: GNU General Public License v3 (GPLv3)
Classifier: Programming Language :: Python :: 3
Classifier: Programming Language :: Python :: 3.8
Requires-Dist: pandas
